ERC/__init__.py
ERC/example.py
ethan_ai_refinery_core-0.0.1.dist-info/METADATA
ethan_ai_refinery_core-0.0.1.dist-info/WHEEL
ethan_ai_refinery_core-0.0.1.dist-info/top_level.txt
ethan_ai_refinery_core-0.0.1.dist-info/RECORD
