Metadata-Version: 2.1
Name: ethan-ai--refinery-core
Version: 0.0.1
Summary: This is a helping lib for a product in ethan-ai named 'Refinery'.
Author-email: Nandi Prasad Madikeri <nandi@ethan-ai.com>
Project-URL: Homepage, https://github.com/pypa/sampleproject
Project-URL: Bug Tracker, https://github.com/pypa/sampleproject/issues
Classifier: Programming Language :: Python :: 3
Classifier: License :: OSI Approved :: MIT License
Classifier: Operating System :: OS Independent
Requires-Python: >=3.8
